https://en.wikibooks.org/wiki/Java_Programming/Byte_Code#Example_2
As an example we can write a simple Foo.java source:public class Foo {
  public static void main(final String[] args) {
    System.out.println("This is a simple example of decompilation using javap");
    a();
    b();
  }
	
  public static void a() {
    System.out.println("Now we are calling a function...");
  }

  public static void b() {
    System.out.println("...and now we are calling b");
  }
}Compile it and then move Foo.java to another directory or delete it if you wish. What can we do with javap and Foo.class ?$javap Fooproduces this result:Compiled from "Foo.java"
public class Foo extends java.lang.Object {
    public Foo();
    public static void main(java.lang.String[]);
    public static void a();
    public static void b();
}As you can see the javac compiler doesn't strip any (public) variable name from the .class file. As a result the names of the functions, their parameters and types of return are exposed. (This is necessary in order for other classes to access them.)Let's do a bit more, try:$javap -c FooCompiled from "Foo.java"
public class Foo extends java.lang.Object{
public Foo();
  Code:
   0:   aload_0
   1:   invokespecial   #1; //Method java/lang/Object."<init>":()V
   4:   return

public static void main(java.lang.String[]);
  Code:
   0:   getstatic       #2; //Field java/lang/System.out:Ljava/io/PrintStream;
   3:   ldc             #3; //String This is a simple example of decompilation using javap
   5:   invokevirtual   #4; //Method java/io/PrintStream.println:(Ljava/lang/String;)V
   8:   invokestatic    #5; //Method a:()V
   11:  invokestatic    #6; //Method b:()V
   14:  return

public static void a();
  Code:
   0:   getstatic       #2; //Field java/lang/System.out:Ljava/io/PrintStream;
   3:   ldc             #7; //String Now we are calling a function...
   5:   invokevirtual   #4; //Method java/io/PrintStream.println:(Ljava/lang/String;)V
   8:   return

public static void b();
  Code:
   0:   getstatic       #2; //Field java/lang/System.out:Ljava/io/PrintStream;
   3:   ldc             #8; //String ...and now we are calling b
   5:   invokevirtual   #4; //Method java/io/PrintStream.println:(Ljava/lang/String;)V
   8:   return

}